odoo9_addon_openeducat_fees-9.0.2.4.0-py2.7-nspkg.pth
odoo9_addon_openeducat_fees-9.0.2.4.0.dist-info/top_level.txt
odoo9_addon_openeducat_fees-9.0.2.4.0.dist-info/WHEEL
odoo9_addon_openeducat_fees-9.0.2.4.0.dist-info/RECORD
odoo9_addon_openeducat_fees-9.0.2.4.0.dist-info/metadata.json
odoo9_addon_openeducat_fees-9.0.2.4.0.dist-info/DESCRIPTION.rst
odoo9_addon_openeducat_fees-9.0.2.4.0.dist-info/METADATA
odoo9_addon_openeducat_fees-9.0.2.4.0.dist-info/namespace_packages.txt
odoo_addons/openeducat_fees/__openerp__.py
odoo_addons/openeducat_fees/__init__.py
odoo_addons/openeducat_fees/security/ir.model.access.csv
odoo_addons/openeducat_fees/models/course.py
odoo_addons/openeducat_fees/models/__init__.py
odoo_addons/openeducat_fees/models/student.py
odoo_addons/openeducat_fees/i18n/openeducat_fees.pot
odoo_addons/openeducat_fees/views/student_view.xml
odoo_addons/openeducat_fees/views/course_view.xml
odoo_addons/openeducat_fees/static/description/openeducat_logo.png
odoo_addons/openeducat_fees/static/description/index.html
odoo_addons/openeducat_fees/static/description/financial.png
odoo_addons/openeducat_fees/static/description/icon.png
odoo_addons/openeducat_fees/static/description/openeducat_fees_banner.jpg
